{
  "slug": "east-side-gallery-history",
  "template": "history",
  "metadata": {
    "title": "柏林东边画廊历史溯源｜冷战墙上的自由呐喊与涂鸦传奇",
    "description": "东边画廊不只是露天画廊，更是柏林墙的残骸、冷战铁幕的见证者。从死亡地带到艺术圣殿，每一幅涂鸦都藏着一段破碎又重生的故事。"
  },
  "breadcrumbs": [
    {
      "label": "首页",
      "href": "/"
    },
    {
      "label": "历史人文",
      "href": "/category/history"
    },
    {
      "label": "德国",
      "href": "/destinations/europe"
    },
    {
      "label": "柏林",
      "href": "/destinations/europe"
    },
    {
      "label": "东边画廊",
      "href": "/attractions/east-side-gallery-history"
    }
  ],
  "hero": {
    "title": "东边画廊・East Side Gallery・德国・柏林",
    "description": ""
  },
  "sections": [
    {
      "title": "1. 导语",
      "bodyHtml": "<p class=\"text-gray-700 leading-relaxed mb-4\"><strong>东边画廊</strong>，全长1.3公里，是世界上最大的露天画廊。它曾是<strong>柏林墙</strong>的一部分，将城市割裂了近三十年。如今，墙上的<strong>105幅涂鸦</strong>成为自由与和平的象征。抛开游玩攻略，走进柏林东边画廊的尘封往事，遇见属于它的时光与传奇。</p>\n              <p class=\"text-gray-700 leading-relaxed mb-4\">---</p>"
    },
    {
      "title": "2. 基本信息",
      "bodyHtml": "<div class=\"grid md:grid-cols-2 gap-6\">\n              <div class=\"space-y-4\">\n                <div class=\"bg-gray-50 p-4 rounded-lg border border-gray-200\">\n  <div class=\"text-sm text-gray-500 mb-1\">中文名称</div>\n  <div class=\"text-gray-900 font-medium\">东边画廊</div>\n</div>\n                <div class=\"bg-gray-50 p-4 rounded-lg border border-gray-200\">\n  <div class=\"text-sm text-gray-500 mb-1\">英文名称</div>\n  <div class=\"text-gray-900 font-medium\">East Side Gallery</div>\n</div>\n                <div class=\"bg-gray-50 p-4 rounded-lg border border-gray-200\">\n  <div class=\"text-sm text-gray-500 mb-1\">正式名称</div>\n  <div class=\"text-gray-900 font-medium\">East Side Gallery</div>\n</div>\n                <div class=\"bg-gray-50 p-4 rounded-lg border border-gray-200\">\n  <div class=\"text-sm text-gray-500 mb-1\">国家</div>\n  <div class=\"text-gray-900 font-medium\">德国</div>\n</div>\n                <div class=\"bg-gray-50 p-4 rounded-lg border border-gray-200\">\n  <div class=\"text-sm text-gray-500 mb-1\">城市</div>\n  <div class=\"text-gray-900 font-medium\">柏林</div>\n</div>\n              </div>\n              \n            </div>"
    },
    {
      "title": "3. 城市/景点起源",
      "bodyHtml": "<div class=\"space-y-4 text-gray-700 leading-relaxed\">\n              <p class=\"text-gray-700 leading-relaxed mb-4\">东边画廊所在的位置，原本是<strong>柏林墙</strong>的<strong>东侧</strong>。1961年8月13日，东德政府在东西柏林之间修筑了这道<strong>混凝土屏障</strong>，全长约155公里。东边画廊这段墙体，属于“<strong>后墙</strong>”（Hinterlandmauer），面向东柏林一侧，原本只是灰色水泥砌成的高墙，毫无装饰。1989年11月9日柏林墙倒塌后，1990年来自21个国家的118位艺术家受邀在这段残存的墙体上创作，于是诞生了“<strong>东边画廊</strong>”。名字中的“画廊”并非传统美术馆，而是一条<strong>露天艺术走廊</strong>，将政治废墟转化为公共艺术空间。</p>\n              <p class=\"text-gray-700 leading-relaxed mb-4\">---</p>\n            </div>"
    },
    {
      "title": "4. 镌刻时光的历史印记",
      "bodyHtml": "<div class=\"space-y-4 text-gray-700 leading-relaxed\">\n              <p class=\"text-gray-700 leading-relaxed mb-4\"><strong>1989年之前</strong>：这段墙是东柏林居民无法靠近的“死亡地带”。墙体高3.6米，配备瞭望塔、探照灯和雷区。<strong>1961年至1989年间</strong>，至少有上百人在试图翻越柏林墙时丧命。东边画廊段附近曾有一个著名的<strong>逃亡隧道</strong>——一位东德青年用数月时间挖通地道，帮助20多人逃往西柏林。</p>\n              <p class=\"text-gray-700 leading-relaxed mb-4\"><strong>1990年创作潮</strong>：柏林墙倒塌后4个月，艺术家们用油漆和刷子将墙体变成了巨大的画布。最著名的作品是<strong>迪米特里·弗鲁贝尔</strong>（Dmitri Vrubel）的《兄弟之吻》——取材于1979年勃列日涅夫和昂纳克的经典照片。这幅画很快成为<strong>冷战终结的符号</strong>，但2009年因风化严重被重绘，艺术家本人再次执笔。</p>\n              <p class=\"text-gray-700 leading-relaxed mb-4\"><strong>2008年保护危机</strong>：随着柏林房地产开发潮，东边画廊曾面临被拆除的威胁。民间组织发起“<strong>拯救东边画廊</strong>”运动，最终这段1.3公里的墙体被列入<strong>文物保护名录</strong>，永久保留。2014年至2016年，墙体进行了全面翻新，艺术家们重返现场，重新绘制褪色的作品。</p>\n              <p class=\"text-gray-700 leading-relaxed mb-4\">---</p>\n            </div>"
    },
    {
      "title": "5. 与这座城共生的名人传奇",
      "bodyHtml": "<div class=\"bg-amber-50 p-6 rounded-lg border border-amber-100 text-gray-700 leading-relaxed\">\n              <p class=\"text-gray-700 leading-relaxed mb-4\"><strong>迪米特里·弗鲁贝尔</strong>（Dmitri Vrubel，1960-2022）</p>\n              <p class=\"text-gray-700 leading-relaxed mb-4\">这位俄罗斯裔德国艺术家，因为《兄弟之吻》而永远与东边画廊绑定。他当时住在柏林，1990年受邀后，用三天时间完成了这幅高3.6米、宽4米的巨作。画中两位政要的<strong>亲吻姿势</strong>，既讽刺又幽默——弗鲁贝尔曾坦言：“我只是想画一个政治笑话。” 2009年原作完全褪色，他不得不重新绘制，却因为版权问题与画廊管理者发生纠纷。他坚持认为：“这幅画属于全世界，不属于任何机构。” 2022年，弗鲁贝尔因癌症去世，东边画廊成了他最后的艺术遗产。</p>\n              <p class=\"text-gray-700 leading-relaxed mb-4\"><strong>大卫·曼斯基</strong>（David Manski）</p>\n              <p class=\"text-gray-700 leading-relaxed mb-4\">这位美国摄影师在1990年春偶然经过东边画廊，拍摄了大量尚未完成的涂鸦和正在工作的艺术家。他的镜头记录下<strong>维克多·阿什</strong>（Victor Ash）的《宇航员》——一个穿着宇航服的男孩，头盔里是地球图案。曼斯基曾说：“墙倒下后，人们用颜料表达恐惧、希望和梦想。那些涂鸦比任何历史书都真实。” 他后来将2000多张底片捐赠给柏林墙博物馆，成为研究东边画廊起源的珍贵档案。</p>\n              <blockquote class=\"border-l-4 border-blue-300 pl-4 italic text-gray-600 my-4 bg-gray-50 py-3 pr-4 rounded-r\"><strong>弗鲁贝尔日记摘录</strong>：“1990年3月，我在墙上画画时，一个西柏林的老人走过来。他说：‘我年轻时在这里站岗，朝东边开枪。现在你画上这个吻，我们还能怎么做？’我告诉他，恨会消失，但是画会留下。”</blockquote>\n              <p class=\"text-gray-700 leading-relaxed mb-4\">---</p>\n            </div>"
    },
    {
      "title": "6. 民间传说与人文风情",
      "bodyHtml": "<div class=\"space-y-4 text-gray-700 leading-relaxed\">\n              <p class=\"text-gray-700 leading-relaxed mb-4\"><strong>“亲吻墙”的爱情巫术</strong>：柏林当地流传一种说法——如果你在《兄弟之吻》涂鸦前，<strong>闭上眼睛，左手放在画中两人的嘴唇间，心里默念爱人的名字，那么你对这个人的感情就会永远像墙上的颜料一样鲜艳</strong>。据说是1990年代一位东德女画家在创作期间发明的“咒语”，她认为墙分隔了太多恋人，唯独这幅画能缝合裂缝。如今，许多情侣专程前来“许愿”。</p>\n              <p class=\"text-gray-700 leading-relaxed mb-4\"><strong>午夜画作“消失”事件</strong>：2013年某个午夜，巡逻员发现墙体上所有涂鸦被<strong>白色油漆覆盖</strong>。第二天社交媒体炸锅，警方调查发现是一名<strong>醉酒的中国游客</strong>误以为这是废弃工地，想帮柏林的“围墙”重新装修。博物馆方最终花了三个月修复，而这位游客被告知“你差点毁掉世界最大的露天画廊”。从此，柏林旅游局在导览手册中加上一行加粗警告：“<strong>请不要手痒——这些墙上的画值几百万欧元</strong>”。</p>\n              <p class=\"text-gray-700 leading-relaxed mb-4\">---</p>\n            </div>"
    },
    {
      "title": "7. 历史回响：读懂这座城的旅行意义",
      "bodyHtml": "<div class=\"bg-gradient-to-r from-blue-50 to-indigo-50 p-6 rounded-lg text-gray-700 leading-relaxed\">\n              <p class=\"text-gray-700 leading-relaxed mb-4\">东边画廊是一道<strong>活着的历史疤痕</strong>。它不像柏林的博物馆岛那样堂皇，却用最粗暴的方式提醒每个路过者：<strong>自由不是免费的</strong>。这里的涂鸦没有一件是单纯的装饰——从《兄弟之吻》的政治讽喻，到《世界人民》的多民族面孔，再到《和平鸽》的白色线条，每一幅都是对过去的分裂的回应，也是对未来的希望。读懂这些墙，你就读懂了冷战时代的柏林人如何在混凝土上刻下自己的声音。这里不是景点，而是一本摊开的<strong>历史画册</strong>。</p>\n              <p class=\"text-gray-700 leading-relaxed mb-4\">👉 想看实地游玩攻略？交通、门票、打卡全攻略，请点击相关游记页。</p>\n            </div>"
    },
    {
      "title": "猜你喜欢",
      "bodyHtml": "<div class=\"grid grid-cols-1 sm:grid-cols-3 gap-6\">\n              <a href=\"/attractions/ploenlein\" class=\"block group\">\n                <div class=\"bg-white rounded-xl overflow-hidden border border-gray-200 hover:shadow-md transition-all duration-300\">\n                  <div class=\"h-32 bg-gray-100 flex items-center justify-center text-4xl font-serif text-gray-300\">\n                    普\n                  </div>\n                  <div class=\"p-4\">\n                    <h4 class=\"font-semibold text-gray-900 group-hover:text-blue-600 transition-colors line-clamp-1\">普伦莱茵</h4>\n                    <p class=\"text-sm text-gray-500 mt-1 line-clamp-1\">Plönlein</p>\n                  </div>\n                </div>\n              </a>\n              <a href=\"/attractions/berlin-anhalter-bahnhof-history\" class=\"block group\">\n                <div class=\"bg-white rounded-xl overflow-hidden border border-gray-200 hover:shadow-md transition-all duration-300\">\n                  <div class=\"h-32 bg-gray-100 flex items-center justify-center text-4xl font-serif text-gray-300\">\n                    柏\n                  </div>\n                  <div class=\"p-4\">\n                    <h4 class=\"font-semibold text-gray-900 group-hover:text-blue-600 transition-colors line-clamp-1\">柏林安哈尔特火车站旧址</h4>\n                    <p class=\"text-sm text-gray-500 mt-1 line-clamp-1\">Berlin Anhalter Bahnhof</p>\n                  </div>\n                </div>\n              </a>\n              <a href=\"/attractions/giessen-botanical-garden\" class=\"block group\">\n                <div class=\"bg-white rounded-xl overflow-hidden border border-gray-200 hover:shadow-md transition-all duration-300\">\n                  <div class=\"h-32 bg-gray-100 flex items-center justify-center text-4xl font-serif text-gray-300\">\n                    吉\n                  </div>\n                  <div class=\"p-4\">\n                    <h4 class=\"font-semibold text-gray-900 group-hover:text-blue-600 transition-colors line-clamp-1\">吉森植物园</h4>\n                    <p class=\"text-sm text-gray-500 mt-1 line-clamp-1\">Giessen Botanical Garden</p>\n                  </div>\n                </div>\n              </a>\n            </div>",
      "relatedItems": [
        {
          "slug": "ploenlein",
          "name": "普伦莱茵",
          "englishName": "Plönlein"
        },
        {
          "slug": "berlin-anhalter-bahnhof-history",
          "name": "柏林安哈尔特火车站旧址",
          "englishName": "Berlin Anhalter Bahnhof"
        },
        {
          "slug": "giessen-botanical-garden",
          "name": "吉森植物园",
          "englishName": "Giessen Botanical Garden"
        }
      ]
    }
  ]
}