{
  "slug": "kirkjufellsfoss-history",
  "template": "history",
  "metadata": {
    "title": "Kirkjufellsfoss历史溯源｜冰岛教会山瀑布的前世今生与地质传奇",
    "description": "冰岛教会山瀑布Kirkjufellsfoss，不仅是摄影圣地，更藏着千年的地质史诗、维京人的敬畏之心与冰岛诗人的孤独足迹。深扒瀑布背后的时光与神话，遇见冰岛灵魂。"
  },
  "breadcrumbs": [
    {
      "label": "首页",
      "href": "/"
    },
    {
      "label": "历史人文",
      "href": "/category/history"
    },
    {
      "label": "冰岛",
      "href": "/destinations/europe"
    },
    {
      "label": "Grundarfjörður（斯奈山半岛）",
      "href": "/destinations/europe"
    },
    {
      "label": "教会山瀑布",
      "href": "/attractions/kirkjufellsfoss-history"
    }
  ],
  "hero": {
    "title": "教会山瀑布・Kirkjufellsfoss・冰岛・Grundarfjörður（斯奈山半岛）",
    "description": ""
  },
  "sections": [
    {
      "title": "1. 导语",
      "bodyHtml": "<p class=\"text-gray-700 leading-relaxed mb-4\">冰岛西部斯奈山半岛的海风，终年吹拂着一座形如教堂尖顶的山峰。</p>\n              <p class=\"text-gray-700 leading-relaxed mb-4\">山脚下，Kirkjufellsfoss（教会山瀑布）奔流直下，落入碧绿的溪谷。</p>\n              <p class=\"text-gray-700 leading-relaxed mb-4\">这并非一道普通的瀑布——它是冰岛地质变迁的活化石，是维京人眼中通往神域的门户，</p>\n              <p class=\"text-gray-700 leading-relaxed mb-4\">也是诗人与探险家反复吟咏的精神图腾。</p>\n              <p class=\"text-gray-700 leading-relaxed mb-4\">抛开游玩攻略，走进Kirkjufellsfoss的尘封往事，遇见冰岛灵魂深处的时光与传奇。</p>"
    },
    {
      "title": "2. 基本信息",
      "bodyHtml": "<div class=\"grid md:grid-cols-2 gap-6\">\n              <div class=\"space-y-4\">\n                <div class=\"bg-gray-50 p-4 rounded-lg border border-gray-200\">\n  <div class=\"text-sm text-gray-500 mb-1\">中文名称</div>\n  <div class=\"text-gray-900 font-medium\">教会山瀑布</div>\n</div>\n                <div class=\"bg-gray-50 p-4 rounded-lg border border-gray-200\">\n  <div class=\"text-sm text-gray-500 mb-1\">英文名称</div>\n  <div class=\"text-gray-900 font-medium\">Kirkjufellsfoss</div>\n</div>\n                <div class=\"bg-gray-50 p-4 rounded-lg border border-gray-200\">\n  <div class=\"text-sm text-gray-500 mb-1\">正式名称</div>\n  <div class=\"text-gray-900 font-medium\">Kirkjufellsfoss</div>\n</div>\n                <div class=\"bg-gray-50 p-4 rounded-lg border border-gray-200\">\n  <div class=\"text-sm text-gray-500 mb-1\">国家</div>\n  <div class=\"text-gray-900 font-medium\">冰岛</div>\n</div>\n                <div class=\"bg-gray-50 p-4 rounded-lg border border-gray-200\">\n  <div class=\"text-sm text-gray-500 mb-1\">城市</div>\n  <div class=\"text-gray-900 font-medium\">Grundarfjörður（斯奈山半岛）</div>\n</div>\n              </div>\n              \n            </div>"
    },
    {
      "title": "3. 城市/景点起源",
      "bodyHtml": "<div class=\"space-y-4 text-gray-700 leading-relaxed\">\n              <p class=\"text-gray-700 leading-relaxed mb-4\">Kirkjufellsfoss并非一座城市，但它的诞生，本身就是一部冰岛地质的史诗。</p>\n              <p class=\"text-gray-700 leading-relaxed mb-4\"><strong>约700万年前</strong>，冰岛还处于火山活动最剧烈的时期。</p>\n              <p class=\"text-gray-700 leading-relaxed mb-4\">玄武岩熔岩流层叠堆积，海水与冰川反复侵蚀，形成了斯奈山半岛起伏的丘陵。</p>\n              <p class=\"text-gray-700 leading-relaxed mb-4\">而Kirkjufell（教会山）的雏形，正是一次巨大冰川擦蚀的杰作。</p>\n              <p class=\"text-gray-700 leading-relaxed mb-4\">冰川退去后，遗留下这座孤立的<strong>岩体</strong>——它由不同硬度的火山岩交替层构成，</p>\n              <p class=\"text-gray-700 leading-relaxed mb-4\">在漫长风化中，较软的岩层被掏空，硬岩保留，最终形成了<strong>教堂尖顶般的轮廓</strong>。</p>\n              <p class=\"text-gray-700 leading-relaxed mb-4\">“Kirkjufell”这个名字，源于冰岛语“Kirkja”（教堂）和“fjall”（山）。</p>\n              <p class=\"text-gray-700 leading-relaxed mb-4\"><strong>最早的文献记载</strong>出现在17世纪，当时冰岛人已经将这座山视为神圣的地标。</p>\n              <p class=\"text-gray-700 leading-relaxed mb-4\">相传，冰岛<strong>基督教化时期</strong>（约公元1000年），传教士曾在这里建造了冰岛第一座木结构教堂？</p>\n              <p class=\"text-gray-700 leading-relaxed mb-4\">——事实是，山脚下的Grundarfjörður镇确实有一座古老教堂，但并非与山同名。</p>\n              <p class=\"text-gray-700 leading-relaxed mb-4\">地名学家推测，之所以叫“教会山”，是因为山峰的造型与当时冰岛乡村常见的<strong>木质尖顶教堂</strong>惊人相似。</p>\n              <p class=\"text-gray-700 leading-relaxed mb-4\"><strong>瀑布本身</strong>（后缀“foss”即瀑布）直到19世纪才被正式定名。</p>\n              <p class=\"text-gray-700 leading-relaxed mb-4\">在更早的维京时代，它被称为“Hamragil”（悬崖峡谷），</p>\n              <p class=\"text-gray-700 leading-relaxed mb-4\">因为水流从高达<strong>50米</strong>的陡峭崖壁跌落，水雾终年不散。</p>\n              <blockquote class=\"border-l-4 border-blue-300 pl-4 italic text-gray-600 my-4 bg-gray-50 py-3 pr-4 rounded-r\">18世纪冰岛牧师兼自然学家Eggert Ólafsson在游记中写道：</blockquote>\n              <blockquote class=\"border-l-4 border-blue-300 pl-4 italic text-gray-600 my-4 bg-gray-50 py-3 pr-4 rounded-r\">“Kirkjufell像一座被遗落的教堂尖塔，矗立在荒原与海洋之间。瀑布的轰鸣，像是教堂的钟声。”</blockquote>\n              <p class=\"text-gray-700 leading-relaxed mb-4\">但真正让Kirkjufellsfoss成为<strong>地质学标本</strong>的，是它独特的“层状”结构。</p>\n              <p class=\"text-gray-700 leading-relaxed mb-4\">瀑布的水源来自<strong>冰川融水</strong>，流经的岩层记录了冰岛近百万年的气候波动。</p>\n              <p class=\"text-gray-700 leading-relaxed mb-4\"><strong>每一层火山灰和沉积物</strong>，都是一次火山喷发或冰川进退的时间戳。</p>\n              <p class=\"text-gray-700 leading-relaxed mb-4\">因此，Kirkjufellsfoss不仅是一道风景，更是一本摊开的<strong>冰岛地质史书</strong>。</p>\n            </div>"
    },
    {
      "title": "4. 镌刻时光的历史印记",
      "bodyHtml": "<div class=\"space-y-4 text-gray-700 leading-relaxed\">\n              <p class=\"text-gray-700 leading-relaxed mb-4\">Kirkjufellsfoss所在的斯奈山半岛，是冰岛最早有人类定居的区域之一。</p>\n              <p class=\"text-gray-700 leading-relaxed mb-4\"><strong>公元9世纪</strong>，北欧维京人乘坐长船抵达这里，用斧头和火把开垦土地。</p>\n              <p class=\"text-gray-700 leading-relaxed mb-4\">教会山脚下肥沃的草场和充沛的淡水，很快吸引了第一批移民。</p>\n              <p class=\"text-gray-700 leading-relaxed mb-4\">他们在瀑布旁建立农场，将其命名为“Staðarhóll”。</p>\n              <p class=\"text-gray-700 leading-relaxed mb-4\"><strong>最早的定居者</strong>名叫Þórður（索尔杜尔），据说他是一位来自挪威的酋长，</p>\n              <p class=\"text-gray-700 leading-relaxed mb-4\">因为部落纷争而流亡至此。他驱车到瀑布下游的峡谷，被水声震慑，认为这里是众神栖息之地。</p>\n              <p class=\"text-gray-700 leading-relaxed mb-4\"><strong>11世纪</strong>，冰岛正式皈依基督教后，教会山瀑布又承载了另一层意义。</p>\n              <p class=\"text-gray-700 leading-relaxed mb-4\">当地居民开始在山脚下举行<strong>露天弥撒</strong>，瀑布的轰鸣被视为神的声音。</p>\n              <p class=\"text-gray-700 leading-relaxed mb-4\"><strong>1227年</strong>的一份土地册记载，Staðarhóll农场拥有“瀑布水域的捕鱼权”。</p>\n              <p class=\"text-gray-700 leading-relaxed mb-4\">当时，瀑布下的深潭盛产<strong>北极红点鲑</strong>，是冬季最重要的蛋白来源。</p>\n              <p class=\"text-gray-700 leading-relaxed mb-4\"><strong>16世纪</strong>，宗教改革风暴席卷冰岛。</p>\n              <p class=\"text-gray-700 leading-relaxed mb-4\">天主教修道院遭查封，许多教堂被改信路德宗的牧师接管。</p>\n              <p class=\"text-gray-700 leading-relaxed mb-4\">教会山周边仍保留着古老的<strong>天主教痕迹</strong>：</p>\n              <p class=\"text-gray-700 leading-relaxed mb-4\">一个被叫作“Kirkjugarður”（教堂花园）的草地上，至今能找到石砌的十字架遗迹。</p>\n              <p class=\"text-gray-700 leading-relaxed mb-4\">这些十字架是<strong>秘密信徒</strong>在深夜刻下的——他们害怕路德宗打压，只能用这种方式寄托信仰。</p>\n              <p class=\"text-gray-700 leading-relaxed mb-4\"><strong>19世纪</strong>，Kirkjufellsfoss迎来了第一位外国探险家。</p>\n              <p class=\"text-gray-700 leading-relaxed mb-4\"><strong>1834年</strong>，法国地质学家<strong>Paul Gaimard</strong>率领“冰岛探险队”抵达这里。</p>\n              <p class=\"text-gray-700 leading-relaxed mb-4\">他花费整整一周测绘瀑布和山体，在日记中惊叹：</p>\n              <p class=\"text-gray-700 leading-relaxed mb-4\">“这座瀑布让我想起了阿尔卑斯山的冰川，但它的色彩——蓝绿交织，像一块被磨碎的祖母绿。”</p>\n              <p class=\"text-gray-700 leading-relaxed mb-4\">Gaimard带走的岩石标本，后来陈列在巴黎自然历史博物馆。</p>\n              <p class=\"text-gray-700 leading-relaxed mb-4\"><strong>20世纪</strong>，教会山瀑布几乎被遗忘。</p>\n              <p class=\"text-gray-700 leading-relaxed mb-4\">直到<strong>1970年代</strong>，冰岛本土摄影师<strong>Sigurgeir Sigurjónsson</strong>偶然在冬日拍下一张瀑布与极光的照片，</p>\n              <p class=\"text-gray-700 leading-relaxed mb-4\">登上《国家地理》杂志，才让这座瀑布第一次进入全球视野。</p>\n            </div>"
    },
    {
      "title": "5. 与这座城共生的名人传奇",
      "bodyHtml": "<div class=\"bg-amber-50 p-6 rounded-lg border border-amber-100 text-gray-700 leading-relaxed\">\n              <p class=\"text-gray-700 leading-relaxed mb-4\"><strong>1. 诗人与地质学家：Jónas Hallgrímsson（1807–1845）</strong></p>\n              <p class=\"text-gray-700 leading-relaxed mb-4\">如果说有一人将冰岛的自然灵魂写进了诗歌，那一定是Jónas Hallgrímsson。</p>\n              <p class=\"text-gray-700 leading-relaxed mb-4\">他出生于冰岛西部Eyjafjörður地区，离斯奈山半岛仅一天马程。</p>\n              <p class=\"text-gray-700 leading-relaxed mb-4\"><strong>1830年</strong>，年轻的Jónas作为地质勘探队员，第一次徒步经过Kirkjufellsfoss。</p>\n              <p class=\"text-gray-700 leading-relaxed mb-4\">他在这里停留了三天，观察岩层、采集苔藓，并用铅笔在笔记本上画下瀑布的素描。</p>\n              <p class=\"text-gray-700 leading-relaxed mb-4\">后来他写道：</p>\n              <blockquote class=\"border-l-4 border-blue-300 pl-4 italic text-gray-600 my-4 bg-gray-50 py-3 pr-4 rounded-r\">“山峰的每一道棱线，都是冰与火的祷文。瀑布的泪水，洗刷着时间的伤痕。”</blockquote>\n              <p class=\"text-gray-700 leading-relaxed mb-4\">Jónas不仅是诗人，更是<strong>冰岛现代地质学之父</strong>。</p>\n              <p class=\"text-gray-700 leading-relaxed mb-4\">他最早指出Kirkjufell的层次结构代表了不同冰期的沉积。</p>\n              <p class=\"text-gray-700 leading-relaxed mb-4\"><strong>1835年</strong>，他在《冰岛自然科学会年刊》上发表论文，将瀑布所在的岩石序列命名为“Kirkjufell层”，</p>\n              <p class=\"text-gray-700 leading-relaxed mb-4\">该命名至今仍被国际地层学使用。</p>\n              <p class=\"text-gray-700 leading-relaxed mb-4\">但Jónas最打动冰岛人的，是他用诗歌唤醒了民族意识。</p>\n              <p class=\"text-gray-700 leading-relaxed mb-4\"><strong>1843年</strong>，他创作了长诗《冰岛》（Ísland），其中提到：</p>\n              <p class=\"text-gray-700 leading-relaxed mb-4\">“在教会山的倒影里，我看见祖先的信仰——像瀑布一样，从未断流。”</p>\n              <p class=\"text-gray-700 leading-relaxed mb-4\">这首诗后来成为冰岛<strong>独立运动</strong>的战歌。</p>\n              <p class=\"text-gray-700 leading-relaxed mb-4\">Jónas在哥本哈根去世后，冰岛人将他的骨灰送回故土，</p>\n              <p class=\"text-gray-700 leading-relaxed mb-4\">并在Grundarfjörður教堂外立了一块石碑，上面刻着那句诗。</p>\n              <p class=\"text-gray-700 leading-relaxed mb-4\"><strong>2. 神秘的女画家：Kjarval的灵感缪斯</strong></p>\n              <p class=\"text-gray-700 leading-relaxed mb-4\">冰岛国宝级画家<strong>Jóhannes Kjarval</strong>（1885–1972），一生痴迷于斯奈山半岛的光影。</p>\n              <p class=\"text-gray-700 leading-relaxed mb-4\"><strong>1938年夏天</strong>，他租下瀑布旁一间废弃的羊圈，住了整整三个月。</p>\n              <p class=\"text-gray-700 leading-relaxed mb-4\">每天清晨，他架起画架，等待第一缕阳光落在尖峰上。</p>\n              <p class=\"text-gray-700 leading-relaxed mb-4\">Kjarval的绘画风格充满超现实主义的魔幻感，</p>\n              <p class=\"text-gray-700 leading-relaxed mb-4\">他笔下的Kirkjufellsfoss有时会变成<strong>一只巨大的眼睛</strong>，瀑布是流下的液体星光。</p>\n              <p class=\"text-gray-700 leading-relaxed mb-4\">关于这段时光，有一个被当地老人反复传颂的轶事：</p>\n              <p class=\"text-gray-700 leading-relaxed mb-4\">一天傍晚，Kjarval画到一半，突然扔下画笔，跑向瀑布。</p>\n              <p class=\"text-gray-700 leading-relaxed mb-4\">他蹲在潭边，双手捧起水喝了一口，然后回头对助手喊：</p>\n              <p class=\"text-gray-700 leading-relaxed mb-4\">“这水里有巨魔的汗水！我要把它画出来！”</p>\n              <p class=\"text-gray-700 leading-relaxed mb-4\">当晚，他完成了一幅名为《巨魔之泪》的油画，</p>\n              <p class=\"text-gray-700 leading-relaxed mb-4\">画面中瀑布变成了血红和墨绿交织的漩涡。</p>\n              <p class=\"text-gray-700 leading-relaxed mb-4\">这幅画现在收藏于<strong>雷克雅未克市美术馆</strong>，价值连城。</p>\n              <p class=\"text-gray-700 leading-relaxed mb-4\">Kjarval在Grundarfjörður留下的影响不止于艺术。</p>\n              <p class=\"text-gray-700 leading-relaxed mb-4\">他雇佣当地渔民做模特，教会他们用颜料画羊皮卷。</p>\n              <p class=\"text-gray-700 leading-relaxed mb-4\">这些渔民的后代，至今仍会每年9月在瀑布旁举办“Kjarval日”，</p>\n              <p class=\"text-gray-700 leading-relaxed mb-4\">用画笔描绘同一座山峰，纪念那位疯狂的画家。</p>\n            </div>"
    },
    {
      "title": "6. 民间传说与人文风情",
      "bodyHtml": "<div class=\"space-y-4 text-gray-700 leading-relaxed\">\n              <p class=\"text-gray-700 leading-relaxed mb-4\">Kirkjufellsfost山背后的<strong>巨魔传说</strong>，是冰岛西部流传最广的故事之一。</p>\n              <p class=\"text-gray-700 leading-relaxed mb-4\">很久很久以前，斯奈山半岛上住着两个不守规矩的巨魔——一个叫<strong>Grímur</strong>，一个叫<strong>Þóra</strong>。</p>\n              <p class=\"text-gray-700 leading-relaxed mb-4\">他们专在夜晚偷村民的羊，还把教堂的钟声当成扰民的噪音。</p>\n              <p class=\"text-gray-700 leading-relaxed mb-4\">一天夜里，Grímur喝醉了，对Þóra说：</p>\n              <p class=\"text-gray-700 leading-relaxed mb-4\">“我要把那个尖顶教堂（Kirkjufell）整个拔起来，扔进海里！”</p>\n              <p class=\"text-gray-700 leading-relaxed mb-4\">Þóra劝他：“天亮前你做不到的，太阳会把我们变成石头。”</p>\n              <p class=\"text-gray-700 leading-relaxed mb-4\">Grímur不听，大步走向山峰，抓住“尖顶”用力往上拔。</p>\n              <p class=\"text-gray-700 leading-relaxed mb-4\">可他发现山脚被瀑布的水流锁住了，怎么也拔不动。</p>\n              <p class=\"text-gray-700 leading-relaxed mb-4\">Þóra急了，跑过来帮忙，她跳进瀑布，试图堵住水源。</p>\n              <p class=\"text-gray-700 leading-relaxed mb-4\">结果水潭里的<strong>水马（Nykur）</strong>浮出水面，用湿漉漉的鬃毛缠住她的腿。</p>\n              <p class=\"text-gray-700 leading-relaxed mb-4\">太阳就在这时从海平面升起。</p>\n              <p class=\"text-gray-700 leading-relaxed mb-4\">第一缕光射过来，Grímur和Þóra同时石化，变成了山体两侧的两块巨岩。</p>\n              <p class=\"text-gray-700 leading-relaxed mb-4\">而瀑布从此带着红色——老人们说，那是Þóra挣扎时流下的血。</p>\n              <p class=\"text-gray-700 leading-relaxed mb-4\">据说，如果你在<strong>仲夏夜的午夜</strong>，站在瀑布下数水流的声音，</p>\n              <p class=\"text-gray-700 leading-relaxed mb-4\">你会听到Þóra的哭喊——低沉的、像大提琴的呜咽。</p>\n              <p class=\"text-gray-700 leading-relaxed mb-4\">而那两块“巨魔石”，在<strong>冬至</strong>的晨雾中，会短暂地动一动眼皮。</p>\n              <p class=\"text-gray-700 leading-relaxed mb-4\">另一个习俗与<strong>丰收有关</strong>：古代冰岛农人认为瀑布的水具有“祝福之力”。</p>\n              <p class=\"text-gray-700 leading-relaxed mb-4\">每年夏至，他们会把一篮新收的干草投入瀑布潭中，祈求羊群平安过冬。</p>\n              <p class=\"text-gray-700 leading-relaxed mb-4\">如果干草在入水后保持不散，就说明教会山的精灵接受了供奉。</p>\n            </div>"
    },
    {
      "title": "7. 历史回响：读懂这座城的旅行意义",
      "bodyHtml": "<div class=\"bg-gradient-to-r from-blue-50 to-indigo-50 p-6 rounded-lg text-gray-700 leading-relaxed\">\n              <p class=\"text-gray-700 leading-relaxed mb-4\">Kirkjufellsfoss不止是一处打卡点。</p>\n              <p class=\"text-gray-700 leading-relaxed mb-4\">它是冰岛地质演化中一枚被精心打磨的宝石，</p>\n              <p class=\"text-gray-700 leading-relaxed mb-4\">是维京人敬畏自然的活祭坛，</p>\n              <p class=\"text-gray-700 leading-relaxed mb-4\">是诗人、画家、地质学家用一生追寻的灵感矿脉。</p>\n              <p class=\"text-gray-700 leading-relaxed mb-4\">读懂它，就是读懂冰岛人如何与冰、火、水共生，</p>\n              <p class=\"text-gray-700 leading-relaxed mb-4\">如何在极端环境中信仰、创造、并留下名字。</p>\n              <p class=\"text-gray-700 leading-relaxed mb-4\">瀑布的水声从未停止，它冲刷着时间的痕迹，也冲刷着每一个游客的心灵。</p>\n              <p class=\"text-gray-700 leading-relaxed mb-4\">如果你被这座瀑布的传奇深深打动，想亲自站在它面前感受那种磅礴与神秘，</p>\n              <p class=\"text-gray-700 leading-relaxed mb-4\">👉 想看实地游玩攻略？交通、门票、打卡全攻略，请点击相关游记页。</p>\n            </div>"
    },
    {
      "title": "猜你喜欢",
      "bodyHtml": "<div class=\"grid grid-cols-1 sm:grid-cols-3 gap-6\">\n              <a href=\"/attractions/stykkisholmskirkja-church\" class=\"block group\">\n                <div class=\"bg-white rounded-xl overflow-hidden border border-gray-200 hover:shadow-md transition-all duration-300\">\n                  <div class=\"h-32 bg-gray-100 flex items-center justify-center text-4xl font-serif text-gray-300\">\n                    斯\n                  </div>\n                  <div class=\"p-4\">\n                    <h4 class=\"font-semibold text-gray-900 group-hover:text-blue-600 transition-colors line-clamp-1\">斯蒂基斯霍尔米教堂</h4>\n                    <p class=\"text-sm text-gray-500 mt-1 line-clamp-1\">Stykkishólmskirkja Church</p>\n                  </div>\n                </div>\n              </a>\n              <a href=\"/attractions/kolugljufur-canyon\" class=\"block group\">\n                <div class=\"bg-white rounded-xl overflow-hidden border border-gray-200 hover:shadow-md transition-all duration-300\">\n                  <div class=\"h-32 bg-gray-100 flex items-center justify-center text-4xl font-serif text-gray-300\">\n                    科\n                  </div>\n                  <div class=\"p-4\">\n                    <h4 class=\"font-semibold text-gray-900 group-hover:text-blue-600 transition-colors line-clamp-1\">科鲁柳弗峡谷</h4>\n                    <p class=\"text-sm text-gray-500 mt-1 line-clamp-1\">Kolugljúfur Canyon</p>\n                  </div>\n                </div>\n              </a>\n              <a href=\"/attractions/landmannalaugar\" class=\"block group\">\n                <div class=\"bg-white rounded-xl overflow-hidden border border-gray-200 hover:shadow-md transition-all duration-300\">\n                  <div class=\"h-32 bg-gray-100 flex items-center justify-center text-4xl font-serif text-gray-300\">\n                    兰\n                  </div>\n                  <div class=\"p-4\">\n                    <h4 class=\"font-semibold text-gray-900 group-hover:text-blue-600 transition-colors line-clamp-1\">兰德曼纳劳卡</h4>\n                    <p class=\"text-sm text-gray-500 mt-1 line-clamp-1\">Landmannalaugar</p>\n                  </div>\n                </div>\n              </a>\n            </div>",
      "relatedItems": [
        {
          "slug": "stykkisholmskirkja-church",
          "name": "斯蒂基斯霍尔米教堂",
          "englishName": "Stykkishólmskirkja Church"
        },
        {
          "slug": "kolugljufur-canyon",
          "name": "科鲁柳弗峡谷",
          "englishName": "Kolugljúfur Canyon"
        },
        {
          "slug": "landmannalaugar",
          "name": "兰德曼纳劳卡",
          "englishName": "Landmannalaugar"
        }
      ]
    }
  ]
}