{
  "slug": "vasa-museum-history",
  "template": "history",
  "metadata": {
    "title": "瓦萨博物馆历史｜瑞典沉船瓦萨号的前世今生与航海传奇",
    "description": "走进斯德哥尔摩的瓦萨博物馆，探寻17世纪战舰瓦萨号的惊人故事：处女航即沉没，333年后重见天日。关于权力、悲剧与民族记忆的传奇，等你揭晓。"
  },
  "breadcrumbs": [
    {
      "label": "首页",
      "href": "/"
    },
    {
      "label": "历史人文",
      "href": "/category/history"
    },
    {
      "label": "瑞典",
      "href": "/destinations/europe"
    },
    {
      "label": "斯德哥尔摩",
      "href": "/destinations/europe"
    },
    {
      "label": "瓦萨博物馆",
      "href": "/attractions/vasa-museum-history"
    }
  ],
  "hero": {
    "title": "瓦萨博物馆・Vasa Museum・瑞典・斯德哥尔摩",
    "description": ""
  },
  "sections": [
    {
      "title": "1. 导语",
      "bodyHtml": "<p class=\"text-gray-700 leading-relaxed mb-4\">在斯德哥尔摩的动物园岛上，有一座专门供奉一艘沉船的神圣殿堂——瓦萨博物馆。这里保存着世界上唯一一艘完整保存的17世纪战舰：<strong>瓦萨号（Vasa）</strong>。</p>\n              <p class=\"text-gray-700 leading-relaxed mb-4\">它于1628年处女航即沉没，又在波罗的海海底沉睡了333年，最终被打捞出水，成为瑞典最珍贵的国宝。</p>\n              <p class=\"text-gray-700 leading-relaxed mb-4\">抛开游玩攻略，走进瓦萨号的故事，遇见属于它的时光与传奇。</p>"
    },
    {
      "title": "2. 基本信息",
      "bodyHtml": "<div class=\"grid md:grid-cols-2 gap-6\">\n              <div class=\"space-y-4\">\n                <div class=\"bg-gray-50 p-4 rounded-lg border border-gray-200\">\n  <div class=\"text-sm text-gray-500 mb-1\">中文名称</div>\n  <div class=\"text-gray-900 font-medium\">瓦萨博物馆</div>\n</div>\n                <div class=\"bg-gray-50 p-4 rounded-lg border border-gray-200\">\n  <div class=\"text-sm text-gray-500 mb-1\">英文名称</div>\n  <div class=\"text-gray-900 font-medium\">Vasa Museum</div>\n</div>\n                <div class=\"bg-gray-50 p-4 rounded-lg border border-gray-200\">\n  <div class=\"text-sm text-gray-500 mb-1\">正式名称</div>\n  <div class=\"text-gray-900 font-medium\">Vasa Museum</div>\n</div>\n                <div class=\"bg-gray-50 p-4 rounded-lg border border-gray-200\">\n  <div class=\"text-sm text-gray-500 mb-1\">国家</div>\n  <div class=\"text-gray-900 font-medium\">瑞典</div>\n</div>\n                <div class=\"bg-gray-50 p-4 rounded-lg border border-gray-200\">\n  <div class=\"text-sm text-gray-500 mb-1\">城市</div>\n  <div class=\"text-gray-900 font-medium\">斯德哥尔摩</div>\n</div>\n              </div>\n              \n            </div>"
    },
    {
      "title": "3. 城市/景点起源",
      "bodyHtml": "<div class=\"space-y-4 text-gray-700 leading-relaxed\">\n              <p class=\"text-gray-700 leading-relaxed mb-4\">严格来说，瓦萨博物馆的“起源”就是瓦萨号沉船的诞生与重生。</p>\n              <p class=\"text-gray-700 leading-relaxed mb-4\">17世纪初，瑞典在国王<strong>古斯塔夫二世·阿道夫（Gustavus Adolphus，1594–1632）</strong>的统治下，正从地区强国向波罗的海霸主迈进。</p>\n              <p class=\"text-gray-700 leading-relaxed mb-4\">为了在“三十年战争”中占据海上优势，国王下令建造当时世界上火力最猛、体型最庞大的战舰——瓦萨号。</p>\n              <p class=\"text-gray-700 leading-relaxed mb-4\">船名取自瑞典王室家族<strong>瓦萨王朝（House of Vasa）</strong>。</p>\n              <p class=\"text-gray-700 leading-relaxed mb-4\">1625年，国王在斯德哥尔摩船坞委托荷兰造船师<strong>亨里克·海伯特森（Henrik Hybertsson）</strong>主持建造。</p>\n              <p class=\"text-gray-700 leading-relaxed mb-4\">然而，亨里克在瓦萨号下水前一年去世，继任者来不及对设计进行充分测试。</p>\n              <p class=\"text-gray-700 leading-relaxed mb-4\">更致命的是，国王在建造过程中不断要求增加上层火炮甲板，导致船体重心过高。</p>\n              <p class=\"text-gray-700 leading-relaxed mb-4\"><strong>1628年8月10日</strong>，瓦萨号在万众瞩目下从斯德哥尔摩港起航。</p>\n              <p class=\"text-gray-700 leading-relaxed mb-4\">仅航行1300米，一阵微风吹来，船体严重倾斜，海水从下层炮窗涌入，随即沉没。</p>\n              <p class=\"text-gray-700 leading-relaxed mb-4\">船上约150人，至少30人随船丧生。</p>\n              <p class=\"text-gray-700 leading-relaxed mb-4\">许多人认为这是“国王的耻辱”，但随后三百多年里，瓦萨号静静躺在32米深的海底，被淤泥与波罗的海的低温完美保护。</p>\n              <p class=\"text-gray-700 leading-relaxed mb-4\">直到<strong>1956年</strong>，业余海洋考古学家<strong>安德斯·弗兰岑（Anders Franzén）</strong>用自制的取样器在港湾中找到了它。</p>\n              <p class=\"text-gray-700 leading-relaxed mb-4\"><strong>1961年4月24日</strong>，经过3年准备，瓦萨号被整体打捞出水。</p>\n              <p class=\"text-gray-700 leading-relaxed mb-4\">为了永久保存这艘历经沧桑的战舰，瑞典政府于<strong>1990年</strong>在打捞地点附近建成了瓦萨博物馆。</p>\n            </div>"
    },
    {
      "title": "4. 镌刻时光的历史印记",
      "bodyHtml": "<div class=\"space-y-4 text-gray-700 leading-relaxed\">\n              <p class=\"text-gray-700 leading-relaxed mb-4\"><strong>1. 处女航的悲剧</strong></p>\n              <p class=\"text-gray-700 leading-relaxed mb-4\">瓦萨号的沉没并非偶然。当时的欧洲战舰设计正在从低矮的划桨船向高耸的风帆战舰过渡，技术尚未成熟。</p>\n              <p class=\"text-gray-700 leading-relaxed mb-4\">国王亲自要求加装两层64门重型青铜火炮，远远超过原始设计负荷。一位荷兰商人在日记中写道：</p>\n              <blockquote class=\"border-l-4 border-blue-300 pl-4 italic text-gray-600 my-4 bg-gray-50 py-3 pr-4 rounded-r\">“当船身摇晃时，连水手都面色苍白。没有人敢相信这样一艘‘水上宫殿’竟然没有做一次倾斜测试。”</blockquote>\n              <p class=\"text-gray-700 leading-relaxed mb-4\">沉没后进行的军事调查无人被追责——因为找不到任何“活着”的罪人，所有责任都归咎于“上帝的旨意”。</p>\n              <p class=\"text-gray-700 leading-relaxed mb-4\"><strong>2. 333年的等待</strong></p>\n              <p class=\"text-gray-700 leading-relaxed mb-4\">瓦萨号沉没后，瑞典政府曾尝试用潜水钟打捞火炮，但从未试图整体起吊。</p>\n              <p class=\"text-gray-700 leading-relaxed mb-4\">直到20世纪50年代，弗兰岑通过查阅历史档案并分析水流，锁定了沉船位置。</p>\n              <p class=\"text-gray-700 leading-relaxed mb-4\">打捞过程本身堪称工程奇迹：潜水员在淤泥中开出6条隧道，穿上钢缆，分步提升。</p>\n              <p class=\"text-gray-700 leading-relaxed mb-4\">由于船体木质完好，<strong>95%的原始构件</strong>被保留，成为17世纪航海史的无价标本。</p>\n              <p class=\"text-gray-700 leading-relaxed mb-4\"><strong>3. 博物馆的诞生</strong></p>\n              <p class=\"text-gray-700 leading-relaxed mb-4\">为了容纳这艘69米长的巨舰，博物馆建筑被设计成一座巨大的“船棚”。</p>\n              <p class=\"text-gray-700 leading-relaxed mb-4\">1990年正式开放，如今每年吸引超过150万游客。</p>\n              <p class=\"text-gray-700 leading-relaxed mb-4\">馆内还展出从瓦萨号上发现的数千件文物：衣物、工具、金币，甚至一具完整的水手骨骼（被称为“长柄勺人”），无声地讲述着那个时代的细节。</p>\n            </div>"
    },
    {
      "title": "5. 与这座城共生的名人传奇",
      "bodyHtml": "<div class=\"bg-amber-50 p-6 rounded-lg border border-amber-100 text-gray-700 leading-relaxed\">\n              <p class=\"text-gray-700 leading-relaxed mb-4\"><strong>1. 造船师：亨里克·海伯特森（生死未卜的荷兰人）</strong></p>\n              <p class=\"text-gray-700 leading-relaxed mb-4\">亨里克是瓦萨号的实际建造者，却未能活到它下水。</p>\n              <p class=\"text-gray-700 leading-relaxed mb-4\">他于1623年携家人来到斯德哥尔摩，成为瑞典皇家海军首席造船师。</p>\n              <p class=\"text-gray-700 leading-relaxed mb-4\">由于国王不断修改设计，亨里克在1625年致信国王：“陛下，若再加一层火炮，船体可能无法承受。”</p>\n              <p class=\"text-gray-700 leading-relaxed mb-4\">但信件石沉大海。<strong>1627年</strong>，他因长期劳累和不满病倒，次年去世。</p>\n              <p class=\"text-gray-700 leading-relaxed mb-4\">他从未看到自己的杰作沉没，但现代学者认为，真正的责任在国王的急功近利。</p>\n              <p class=\"text-gray-700 leading-relaxed mb-4\">瓦萨号的名字“Vasa”其实是瑞典语“麦秆束”的变体（瓦萨王朝的徽章图案），而亨里克的名字却鲜少被提及——直到博物馆特意为他设立了一面历史墙。</p>\n              <p class=\"text-gray-700 leading-relaxed mb-4\"><strong>2. 打捞者：安德斯·弗兰岑（业余考古学家的执念）</strong></p>\n              <p class=\"text-gray-700 leading-relaxed mb-4\">安德斯·弗兰岑并非职业考古学家，而是一名海军顾问和业余历史爱好者。</p>\n              <p class=\"text-gray-700 leading-relaxed mb-4\">他从小痴迷于瓦萨号的故事，坚信沉船仍然完好。</p>\n              <p class=\"text-gray-700 leading-relaxed mb-4\">在50年代，他查阅了所有相关的瑞典文档案，发现沉船位置被记录为“斯德哥尔摩港湾的Beckholmen岛附近”。</p>\n              <p class=\"text-gray-700 leading-relaxed mb-4\">他自费制作了一个长柄取样器，在海底反复钻孔。</p>\n              <p class=\"text-gray-700 leading-relaxed mb-4\"><strong>1956年8月25日</strong>，他的取样器带上来一块黑色橡木——瓦萨号的一个船壳板。</p>\n              <p class=\"text-gray-700 leading-relaxed mb-4\">他在日记中写道：</p>\n              <blockquote class=\"border-l-4 border-blue-300 pl-4 italic text-gray-600 my-4 bg-gray-50 py-3 pr-4 rounded-r\">“那一刻，我的手在颤抖。我知道，我找到了瑞典历史上最伟大的沉睡者。”</blockquote>\n              <p class=\"text-gray-700 leading-relaxed mb-4\">打捞成功后，弗兰岑放弃所有专利，将全部解说权献给国家。他成为全球海洋考古学的奠基人之一。</p>\n              <p class=\"text-gray-700 leading-relaxed mb-4\"><strong>3. 古斯塔夫二世·阿道夫（国王的野望与遗憾）</strong></p>\n              <p class=\"text-gray-700 leading-relaxed mb-4\">虽然国王并非“小众名人”，但他是瓦萨号悲剧的直接推手。</p>\n              <p class=\"text-gray-700 leading-relaxed mb-4\">他是一位军事天才，在三十年战争中革新了步兵战术，被称为“北方雄狮”。</p>\n              <p class=\"text-gray-700 leading-relaxed mb-4\">但他对瓦萨号的设计干预，暴露了他在工程上的无知。</p>\n              <p class=\"text-gray-700 leading-relaxed mb-4\">当时，瑞典正与波兰、丹麦争霸，他需要一艘“精神象征”般的战舰来震慑对手。</p>\n              <p class=\"text-gray-700 leading-relaxed mb-4\">瓦萨号的沉没让他极为难堪，他下令对事件保密，并终止了类似大型战舰的建造计划。</p>\n              <p class=\"text-gray-700 leading-relaxed mb-4\">直到今天，瓦萨博物馆的展板上仍引用他的名言：</p>\n              <blockquote class=\"border-l-4 border-blue-300 pl-4 italic text-gray-600 my-4 bg-gray-50 py-3 pr-4 rounded-r\">“若上帝不给我胜利，至少给我一艘不沉的船。”</blockquote>\n            </div>"
    },
    {
      "title": "6. 民间传说与人文风情",
      "bodyHtml": "<div class=\"space-y-4 text-gray-700 leading-relaxed\">\n              <p class=\"text-gray-700 leading-relaxed mb-4\">关于瓦萨号，最著名的传说是“船上的诅咒”。</p>\n              <p class=\"text-gray-700 leading-relaxed mb-4\">据说，在瓦萨号下水前夜，一位年迈的萨米女巫来到船坞，用沙哑的声音预言：“这艘船载着王室的傲慢，它将带着那些嘲笑大海的人沉入黑暗。”</p>\n              <p class=\"text-gray-700 leading-relaxed mb-4\">卫兵将她赶走，但第二天，瓦萨号真的沉没了。</p>\n              <p class=\"text-gray-700 leading-relaxed mb-4\">更神秘的是，在打捞过程中，潜水员多次报告感到“有水手的手在触碰自己的脖子”。</p>\n              <p class=\"text-gray-700 leading-relaxed mb-4\">有人声称在深夜的博物馆里，听到木地板上传来沉重的脚步声，以及隐约的北欧古语祈祷声。</p>\n              <p class=\"text-gray-700 leading-relaxed mb-4\">另一个广为流传的轶事是：</p>\n              <p class=\"text-gray-700 leading-relaxed mb-4\">一名船员的骷髅被发现时，手中紧紧握着一把小刀——考古学家推测，他在沉没前试图割断缆绳逃生，但最终被困。</p>\n              <p class=\"text-gray-700 leading-relaxed mb-4\">这具骨骼现在被陈列在博物馆中，面部通过3D复原技术被还原，仿佛仍在凝视着前来参观的世人。</p>\n              <p class=\"text-gray-700 leading-relaxed mb-4\">当地渔民间流传着一种习俗：每当经过博物馆所在的海域，他们会向水中抛撒一枚铜币，以示对逝者的敬意。</p>\n              <blockquote class=\"border-l-4 border-blue-300 pl-4 italic text-gray-600 my-4 bg-gray-50 py-3 pr-4 rounded-r\">“瓦萨号是瑞典的眼泪，但也是它的心脏。” —— 一位老渔民的口头禅。</blockquote>\n            </div>"
    },
    {
      "title": "7. 历史回响：读懂这座城的旅行意义",
      "bodyHtml": "<div class=\"bg-gradient-to-r from-blue-50 to-indigo-50 p-6 rounded-lg text-gray-700 leading-relaxed\">\n              <p class=\"text-gray-700 leading-relaxed mb-4\">瓦萨博物馆不仅仅是一座展示沉船的建筑物，它是17世纪瑞典帝国的缩影，一堂关于人类傲慢与自然力量的实物课堂。</p>\n              <p class=\"text-gray-700 leading-relaxed mb-4\">每一条船肋、每一门火炮都诉说着一个国王、一群工匠和一个时代的命运。</p>\n              <p class=\"text-gray-700 leading-relaxed mb-4\">它提醒我们：最伟大的野心也可能在最短暂的瞬间化为泡沫。</p>\n              <p class=\"text-gray-700 leading-relaxed mb-4\">同时，它也是海洋考古学的一座丰碑——人类如何用耐心和技术让百年前的遗产重见天日。</p>\n              <p class=\"text-gray-700 leading-relaxed mb-4\">读懂瓦萨博物馆，就是读懂瑞典的民族性格：坚韧、务实、对历史的敬畏。</p>\n              <p class=\"text-gray-700 leading-relaxed mb-4\">👉 想看实地游玩攻略？交通、门票、打卡全攻略，请点击相关游记页。</p>\n            </div>"
    },
    {
      "title": "猜你喜欢",
      "bodyHtml": "<div class=\"grid grid-cols-1 sm:grid-cols-3 gap-6\">\n              <a href=\"/attractions/kalmar-castle\" class=\"block group\">\n                <div class=\"bg-white rounded-xl overflow-hidden border border-gray-200 hover:shadow-md transition-all duration-300\">\n                  <div class=\"h-32 bg-gray-100 flex items-center justify-center text-4xl font-serif text-gray-300\">\n                    卡\n                  </div>\n                  <div class=\"p-4\">\n                    <h4 class=\"font-semibold text-gray-900 group-hover:text-blue-600 transition-colors line-clamp-1\">卡尔马城堡</h4>\n                    <p class=\"text-sm text-gray-500 mt-1 line-clamp-1\">Kalmar Castle</p>\n                  </div>\n                </div>\n              </a>\n              <a href=\"/attractions/abba-the-museum\" class=\"block group\">\n                <div class=\"bg-white rounded-xl overflow-hidden border border-gray-200 hover:shadow-md transition-all duration-300\">\n                  <div class=\"h-32 bg-gray-100 flex items-center justify-center text-4xl font-serif text-gray-300\">\n                    A\n                  </div>\n                  <div class=\"p-4\">\n                    <h4 class=\"font-semibold text-gray-900 group-hover:text-blue-600 transition-colors line-clamp-1\">ABBA博物馆</h4>\n                    <p class=\"text-sm text-gray-500 mt-1 line-clamp-1\">ABBA The Museum</p>\n                  </div>\n                </div>\n              </a>\n              <a href=\"/attractions/eksjo-old-town\" class=\"block group\">\n                <div class=\"bg-white rounded-xl overflow-hidden border border-gray-200 hover:shadow-md transition-all duration-300\">\n                  <div class=\"h-32 bg-gray-100 flex items-center justify-center text-4xl font-serif text-gray-300\">\n                    埃\n                  </div>\n                  <div class=\"p-4\">\n                    <h4 class=\"font-semibold text-gray-900 group-hover:text-blue-600 transition-colors line-clamp-1\">埃克舍老城</h4>\n                    <p class=\"text-sm text-gray-500 mt-1 line-clamp-1\">Eksjö Old Town</p>\n                  </div>\n                </div>\n              </a>\n            </div>",
      "relatedItems": [
        {
          "slug": "kalmar-castle",
          "name": "卡尔马城堡",
          "englishName": "Kalmar Castle"
        },
        {
          "slug": "abba-the-museum",
          "name": "ABBA博物馆",
          "englishName": "ABBA The Museum"
        },
        {
          "slug": "eksjo-old-town",
          "name": "埃克舍老城",
          "englishName": "Eksjö Old Town"
        }
      ]
    }
  ]
}